yet_another_pypi_test/__init__.py
yet_another_pypi_test-0.5.0.dist-info/METADATA
yet_another_pypi_test-0.5.0.dist-info/WHEEL
yet_another_pypi_test-0.5.0.dist-info/RECORD
