Metadata-Version: 2.1
Name: Yet-another-pypi-test
Version: 0.5.0
Summary: Test PyPI packaging
Author: Volk Dmitry
Author-email: volk.dmitry@gmail.com
Requires-Python: >=3.11,<4.0
Classifier: Programming Language :: Python :: 3
Classifier: Programming Language :: Python :: 3.11
Classifier: Programming Language :: Python :: 3.12
